earthmover/VERSION.txt
earthmover/__init__.py
earthmover/__main__.py
earthmover/earthmover.py
earthmover/error_handler.py
earthmover/graph.py
earthmover/init.py
earthmover/package.py
earthmover/runs_file.py
earthmover/util.py
earthmover/yaml_parser.py
earthmover/include/starter_project/README.md
earthmover/include/starter_project/earthmover.yaml
earthmover/nodes/__init__.py
earthmover/nodes/destination.py
earthmover/nodes/node.py
earthmover/nodes/source.py
earthmover/nodes/transformation.py
earthmover/operations/__init__.py
earthmover/operations/column.py
earthmover/operations/dataframe.py
earthmover/operations/groupby.py
earthmover/operations/operation.py
earthmover/operations/row.py
earthmover/tests/earthmover.yaml
earthmover/tests/expected/animals.jsonl
earthmover/tests/expected/big_cats.jsonl
earthmover/tests/expected/cities_code_stats.jsonl
earthmover/tests/expected/cities_weather.jsonl
earthmover/tests/expected/families.jsonl
earthmover/tests/expected/melt_basic_output.jsonl
earthmover/tests/expected/melt_no_id_vars_output.jsonl
earthmover/tests/expected/melt_no_value_vars_output.jsonl
earthmover/tests/expected/melt_pivot_roundtrip_output.jsonl
earthmover/tests/expected/melt_single_vars_output.jsonl
earthmover/tests/expected/pivot_basic_output.jsonl
earthmover/tests/expected/species_count_by_zoo.jsonl
earthmover/tests/expected/total_of_each_species.jsonl
earthmover/tests/expected/wildcards.jsonl
earthmover/tests/expected/zoo_count_by_species.jsonl
earthmover/tests/expected/zoo_count_by_year_founded.jsonl
earthmover/tests/outputs/animals.jsonl
earthmover/tests/outputs/big_cats.jsonl
earthmover/tests/outputs/cities_code_stats.jsonl
earthmover/tests/outputs/cities_weather.jsonl
earthmover/tests/outputs/families.jsonl
earthmover/tests/outputs/melt_basic_output.jsonl
earthmover/tests/outputs/melt_no_id_vars_output.jsonl
earthmover/tests/outputs/melt_no_value_vars_output.jsonl
earthmover/tests/outputs/melt_pivot_roundtrip_output.jsonl
earthmover-0.4.8.dist-info/licenses/LICENSE
earthmover-0.4.8.dist-info/METADATA
earthmover-0.4.8.dist-info/WHEEL
earthmover-0.4.8.dist-info/dependency_links.txt
earthmover-0.4.8.dist-info/entry_points.txt
earthmover-0.4.8.dist-info/top_level.txt
earthmover-0.4.8.dist-info/RECORD
